{"assets/camera/brightness.svg":["assets/camera/brightness.svg"],"assets/camera/camera.svg":["assets/camera/camera.svg"],"assets/camera/full_screen.svg":["assets/camera/full_screen.svg"],"assets/camera/mirror.svg":["assets/camera/mirror.svg"],"assets/camera/pause.svg":["assets/camera/pause.svg"],"assets/camera/rotate.svg":["assets/camera/rotate.svg"],"assets/camera/zoomin.svg":["assets/camera/zoomin.svg"],"assets/camera/zoomout.svg":["assets/camera/zoomout.svg"],"assets/gif/not found.gif":["assets/gif/not found.gif"],"assets/hover/eraser.svg":["assets/hover/eraser.svg"],"assets/hover/image.svg":["assets/hover/image.svg"],"assets/hover/math.svg":["assets/hover/math.svg"],"assets/hover/messenger.svg":["assets/hover/messenger.svg"],"assets/hover/pen.svg":["assets/hover/pen.svg"],"assets/hover/profile.svg":["assets/hover/profile.svg"],"assets/hover/record.svg":["assets/hover/record.svg"],"assets/hover/save.svg":["assets/hover/save.svg"],"assets/hover/selection.svg":["assets/hover/selection.svg"],"assets/hover/shapes.svg":["assets/hover/shapes.svg"],"assets/hover/text.svg":["assets/hover/text.svg"],"assets/hover/text1.svg":["assets/hover/text1.svg"],"assets/hover/text2.svg":["assets/hover/text2.svg"],"assets/icons/Wriety_logo.png":["assets/icons/Wriety_logo.png"],"assets/icons/protractor_angle.png":["assets/icons/protractor_angle.png"],"assets/icons/protractor_arc.png":["assets/icons/protractor_arc.png"],"assets/icons/protractor_fill.png":["assets/icons/protractor_fill.png"],"assets/images/Wriety loading icon.gif":["assets/images/Wriety loading icon.gif"],"assets/images/equipments/compass_body.png":["assets/images/equipments/compass_body.png"],"assets/images/equipments/compass_leg_l.png":["assets/images/equipments/compass_leg_l.png"],"assets/images/equipments/compass_leg_r.png":["assets/images/equipments/compass_leg_r.png"],"assets/images/equipments/protractor.png":["assets/images/equipments/protractor.png"],"assets/images/equipments/ruler.jpg":["assets/images/equipments/ruler.jpg"],"assets/images/equipments/ruler.png":["assets/images/equipments/ruler.png"],"assets/images/equipments/setSquare.svg":["assets/images/equipments/setSquare.svg"],"assets/images/equipments/set_square.png":["assets/images/equipments/set_square.png"],"assets/images/logo.png":["assets/images/logo.png"],"assets/images/logoImage.png":["assets/images/logoImage.png"],"assets/images/magicpen.gif":["assets/images/magicpen.gif"],"assets/images/milky_way.jpg":["assets/images/milky_way.jpg"],"assets/images/waiting.gif":["assets/images/waiting.gif"],"assets/images/waiting_new.gif":["assets/images/waiting_new.gif"],"assets/magic_icons/0.svg":["assets/magic_icons/0.svg"],"assets/magic_icons/1.svg":["assets/magic_icons/1.svg"],"assets/magic_icons/10.svg":["assets/magic_icons/10.svg"],"assets/magic_icons/100.svg":["assets/magic_icons/100.svg"],"assets/magic_icons/101.svg":["assets/magic_icons/101.svg"],"assets/magic_icons/102.svg":["assets/magic_icons/102.svg"],"assets/magic_icons/103.svg":["assets/magic_icons/103.svg"],"assets/magic_icons/104.svg":["assets/magic_icons/104.svg"],"assets/magic_icons/105.svg":["assets/magic_icons/105.svg"],"assets/magic_icons/106.svg":["assets/magic_icons/106.svg"],"assets/magic_icons/107.svg":["assets/magic_icons/107.svg"],"assets/magic_icons/108.svg":["assets/magic_icons/108.svg"],"assets/magic_icons/109.svg":["assets/magic_icons/109.svg"],"assets/magic_icons/11.svg":["assets/magic_icons/11.svg"],"assets/magic_icons/110.svg":["assets/magic_icons/110.svg"],"assets/magic_icons/111.svg":["assets/magic_icons/111.svg"],"assets/magic_icons/112.svg":["assets/magic_icons/112.svg"],"assets/magic_icons/113.svg":["assets/magic_icons/113.svg"],"assets/magic_icons/114.svg":["assets/magic_icons/114.svg"],"assets/magic_icons/115.svg":["assets/magic_icons/115.svg"],"assets/magic_icons/116.svg":["assets/magic_icons/116.svg"],"assets/magic_icons/117.svg":["assets/magic_icons/117.svg"],"assets/magic_icons/118.svg":["assets/magic_icons/118.svg"],"assets/magic_icons/119.svg":["assets/magic_icons/119.svg"],"assets/magic_icons/12.svg":["assets/magic_icons/12.svg"],"assets/magic_icons/120.svg":["assets/magic_icons/120.svg"],"assets/magic_icons/121.svg":["assets/magic_icons/121.svg"],"assets/magic_icons/122.svg":["assets/magic_icons/122.svg"],"assets/magic_icons/123.svg":["assets/magic_icons/123.svg"],"assets/magic_icons/124.svg":["assets/magic_icons/124.svg"],"assets/magic_icons/125.svg":["assets/magic_icons/125.svg"],"assets/magic_icons/126.svg":["assets/magic_icons/126.svg"],"assets/magic_icons/127.svg":["assets/magic_icons/127.svg"],"assets/magic_icons/128.svg":["assets/magic_icons/128.svg"],"assets/magic_icons/129.svg":["assets/magic_icons/129.svg"],"assets/magic_icons/13.svg":["assets/magic_icons/13.svg"],"assets/magic_icons/130.svg":["assets/magic_icons/130.svg"],"assets/magic_icons/131.svg":["assets/magic_icons/131.svg"],"assets/magic_icons/132.svg":["assets/magic_icons/132.svg"],"assets/magic_icons/133.svg":["assets/magic_icons/133.svg"],"assets/magic_icons/134.svg":["assets/magic_icons/134.svg"],"assets/magic_icons/135.svg":["assets/magic_icons/135.svg"],"assets/magic_icons/136.svg":["assets/magic_icons/136.svg"],"assets/magic_icons/137.svg":["assets/magic_icons/137.svg"],"assets/magic_icons/138.svg":["assets/magic_icons/138.svg"],"assets/magic_icons/139.svg":["assets/magic_icons/139.svg"],"assets/magic_icons/14.svg":["assets/magic_icons/14.svg"],"assets/magic_icons/140.svg":["assets/magic_icons/140.svg"],"assets/magic_icons/141.svg":["assets/magic_icons/141.svg"],"assets/magic_icons/142.svg":["assets/magic_icons/142.svg"],"assets/magic_icons/143.svg":["assets/magic_icons/143.svg"],"assets/magic_icons/144.svg":["assets/magic_icons/144.svg"],"assets/magic_icons/145.svg":["assets/magic_icons/145.svg"],"assets/magic_icons/146.svg":["assets/magic_icons/146.svg"],"assets/magic_icons/147.svg":["assets/magic_icons/147.svg"],"assets/magic_icons/148.svg":["assets/magic_icons/148.svg"],"assets/magic_icons/149.svg":["assets/magic_icons/149.svg"],"assets/magic_icons/15.svg":["assets/magic_icons/15.svg"],"assets/magic_icons/150.svg":["assets/magic_icons/150.svg"],"assets/magic_icons/151.svg":["assets/magic_icons/151.svg"],"assets/magic_icons/152.svg":["assets/magic_icons/152.svg"],"assets/magic_icons/153.svg":["assets/magic_icons/153.svg"],"assets/magic_icons/154.svg":["assets/magic_icons/154.svg"],"assets/magic_icons/155.svg":["assets/magic_icons/155.svg"],"assets/magic_icons/156.svg":["assets/magic_icons/156.svg"],"assets/magic_icons/157.svg":["assets/magic_icons/157.svg"],"assets/magic_icons/158.svg":["assets/magic_icons/158.svg"],"assets/magic_icons/159.svg":["assets/magic_icons/159.svg"],"assets/magic_icons/16.svg":["assets/magic_icons/16.svg"],"assets/magic_icons/160.svg":["assets/magic_icons/160.svg"],"assets/magic_icons/161.svg":["assets/magic_icons/161.svg"],"assets/magic_icons/162.svg":["assets/magic_icons/162.svg"],"assets/magic_icons/163.svg":["assets/magic_icons/163.svg"],"assets/magic_icons/164.svg":["assets/magic_icons/164.svg"],"assets/magic_icons/165.svg":["assets/magic_icons/165.svg"],"assets/magic_icons/166.svg":["assets/magic_icons/166.svg"],"assets/magic_icons/167.svg":["assets/magic_icons/167.svg"],"assets/magic_icons/168.svg":["assets/magic_icons/168.svg"],"assets/magic_icons/169.svg":["assets/magic_icons/169.svg"],"assets/magic_icons/17.svg":["assets/magic_icons/17.svg"],"assets/magic_icons/170.svg":["assets/magic_icons/170.svg"],"assets/magic_icons/171.svg":["assets/magic_icons/171.svg"],"assets/magic_icons/172.svg":["assets/magic_icons/172.svg"],"assets/magic_icons/173.svg":["assets/magic_icons/173.svg"],"assets/magic_icons/174.svg":["assets/magic_icons/174.svg"],"assets/magic_icons/175.svg":["assets/magic_icons/175.svg"],"assets/magic_icons/176.svg":["assets/magic_icons/176.svg"],"assets/magic_icons/177.svg":["assets/magic_icons/177.svg"],"assets/magic_icons/178.svg":["assets/magic_icons/178.svg"],"assets/magic_icons/179.svg":["assets/magic_icons/179.svg"],"assets/magic_icons/18.svg":["assets/magic_icons/18.svg"],"assets/magic_icons/180.svg":["assets/magic_icons/180.svg"],"assets/magic_icons/181.svg":["assets/magic_icons/181.svg"],"assets/magic_icons/182.svg":["assets/magic_icons/182.svg"],"assets/magic_icons/183.svg":["assets/magic_icons/183.svg"],"assets/magic_icons/184.svg":["assets/magic_icons/184.svg"],"assets/magic_icons/185.svg":["assets/magic_icons/185.svg"],"assets/magic_icons/186.svg":["assets/magic_icons/186.svg"],"assets/magic_icons/187.svg":["assets/magic_icons/187.svg"],"assets/magic_icons/188.svg":["assets/magic_icons/188.svg"],"assets/magic_icons/189.svg":["assets/magic_icons/189.svg"],"assets/magic_icons/19.svg":["assets/magic_icons/19.svg"],"assets/magic_icons/190.svg":["assets/magic_icons/190.svg"],"assets/magic_icons/191.svg":["assets/magic_icons/191.svg"],"assets/magic_icons/192.svg":["assets/magic_icons/192.svg"],"assets/magic_icons/193.svg":["assets/magic_icons/193.svg"],"assets/magic_icons/194.svg":["assets/magic_icons/194.svg"],"assets/magic_icons/195.svg":["assets/magic_icons/195.svg"],"assets/magic_icons/196.svg":["assets/magic_icons/196.svg"],"assets/magic_icons/197.svg":["assets/magic_icons/197.svg"],"assets/magic_icons/198.svg":["assets/magic_icons/198.svg"],"assets/magic_icons/199.svg":["assets/magic_icons/199.svg"],"assets/magic_icons/2.svg":["assets/magic_icons/2.svg"],"assets/magic_icons/20.svg":["assets/magic_icons/20.svg"],"assets/magic_icons/200.svg":["assets/magic_icons/200.svg"],"assets/magic_icons/201.svg":["assets/magic_icons/201.svg"],"assets/magic_icons/202.svg":["assets/magic_icons/202.svg"],"assets/magic_icons/203.svg":["assets/magic_icons/203.svg"],"assets/magic_icons/204.svg":["assets/magic_icons/204.svg"],"assets/magic_icons/205.svg":["assets/magic_icons/205.svg"],"assets/magic_icons/206.svg":["assets/magic_icons/206.svg"],"assets/magic_icons/207.svg":["assets/magic_icons/207.svg"],"assets/magic_icons/208.svg":["assets/magic_icons/208.svg"],"assets/magic_icons/209.svg":["assets/magic_icons/209.svg"],"assets/magic_icons/21.svg":["assets/magic_icons/21.svg"],"assets/magic_icons/210.svg":["assets/magic_icons/210.svg"],"assets/magic_icons/211.svg":["assets/magic_icons/211.svg"],"assets/magic_icons/212.svg":["assets/magic_icons/212.svg"],"assets/magic_icons/213.svg":["assets/magic_icons/213.svg"],"assets/magic_icons/214.svg":["assets/magic_icons/214.svg"],"assets/magic_icons/215.svg":["assets/magic_icons/215.svg"],"assets/magic_icons/216.svg":["assets/magic_icons/216.svg"],"assets/magic_icons/217.svg":["assets/magic_icons/217.svg"],"assets/magic_icons/218.svg":["assets/magic_icons/218.svg"],"assets/magic_icons/219.svg":["assets/magic_icons/219.svg"],"assets/magic_icons/22.svg":["assets/magic_icons/22.svg"],"assets/magic_icons/220.svg":["assets/magic_icons/220.svg"],"assets/magic_icons/221.svg":["assets/magic_icons/221.svg"],"assets/magic_icons/222.svg":["assets/magic_icons/222.svg"],"assets/magic_icons/223.svg":["assets/magic_icons/223.svg"],"assets/magic_icons/224.svg":["assets/magic_icons/224.svg"],"assets/magic_icons/225.svg":["assets/magic_icons/225.svg"],"assets/magic_icons/226.svg":["assets/magic_icons/226.svg"],"assets/magic_icons/227.svg":["assets/magic_icons/227.svg"],"assets/magic_icons/228.svg":["assets/magic_icons/228.svg"],"assets/magic_icons/229.svg":["assets/magic_icons/229.svg"],"assets/magic_icons/23.svg":["assets/magic_icons/23.svg"],"assets/magic_icons/230.svg":["assets/magic_icons/230.svg"],"assets/magic_icons/231.svg":["assets/magic_icons/231.svg"],"assets/magic_icons/232.svg":["assets/magic_icons/232.svg"],"assets/magic_icons/233.svg":["assets/magic_icons/233.svg"],"assets/magic_icons/234.svg":["assets/magic_icons/234.svg"],"assets/magic_icons/235.svg":["assets/magic_icons/235.svg"],"assets/magic_icons/236.svg":["assets/magic_icons/236.svg"],"assets/magic_icons/237.svg":["assets/magic_icons/237.svg"],"assets/magic_icons/238.svg":["assets/magic_icons/238.svg"],"assets/magic_icons/239.svg":["assets/magic_icons/239.svg"],"assets/magic_icons/24.svg":["assets/magic_icons/24.svg"],"assets/magic_icons/240.svg":["assets/magic_icons/240.svg"],"assets/magic_icons/241.svg":["assets/magic_icons/241.svg"],"assets/magic_icons/242.svg":["assets/magic_icons/242.svg"],"assets/magic_icons/243.svg":["assets/magic_icons/243.svg"],"assets/magic_icons/244.svg":["assets/magic_icons/244.svg"],"assets/magic_icons/245.svg":["assets/magic_icons/245.svg"],"assets/magic_icons/246.svg":["assets/magic_icons/246.svg"],"assets/magic_icons/247.svg":["assets/magic_icons/247.svg"],"assets/magic_icons/248.svg":["assets/magic_icons/248.svg"],"assets/magic_icons/249.svg":["assets/magic_icons/249.svg"],"assets/magic_icons/25.svg":["assets/magic_icons/25.svg"],"assets/magic_icons/250.svg":["assets/magic_icons/250.svg"],"assets/magic_icons/251.svg":["assets/magic_icons/251.svg"],"assets/magic_icons/252.svg":["assets/magic_icons/252.svg"],"assets/magic_icons/253.svg":["assets/magic_icons/253.svg"],"assets/magic_icons/254.svg":["assets/magic_icons/254.svg"],"assets/magic_icons/255.svg":["assets/magic_icons/255.svg"],"assets/magic_icons/256.svg":["assets/magic_icons/256.svg"],"assets/magic_icons/257.svg":["assets/magic_icons/257.svg"],"assets/magic_icons/258.svg":["assets/magic_icons/258.svg"],"assets/magic_icons/259.svg":["assets/magic_icons/259.svg"],"assets/magic_icons/26.svg":["assets/magic_icons/26.svg"],"assets/magic_icons/260.svg":["assets/magic_icons/260.svg"],"assets/magic_icons/261.svg":["assets/magic_icons/261.svg"],"assets/magic_icons/262.svg":["assets/magic_icons/262.svg"],"assets/magic_icons/263.svg":["assets/magic_icons/263.svg"],"assets/magic_icons/264.svg":["assets/magic_icons/264.svg"],"assets/magic_icons/265.svg":["assets/magic_icons/265.svg"],"assets/magic_icons/266.svg":["assets/magic_icons/266.svg"],"assets/magic_icons/267.svg":["assets/magic_icons/267.svg"],"assets/magic_icons/268.svg":["assets/magic_icons/268.svg"],"assets/magic_icons/269.svg":["assets/magic_icons/269.svg"],"assets/magic_icons/27.svg":["assets/magic_icons/27.svg"],"assets/magic_icons/270.svg":["assets/magic_icons/270.svg"],"assets/magic_icons/271.svg":["assets/magic_icons/271.svg"],"assets/magic_icons/272.svg":["assets/magic_icons/272.svg"],"assets/magic_icons/273.svg":["assets/magic_icons/273.svg"],"assets/magic_icons/274.svg":["assets/magic_icons/274.svg"],"assets/magic_icons/275.svg":["assets/magic_icons/275.svg"],"assets/magic_icons/276.svg":["assets/magic_icons/276.svg"],"assets/magic_icons/277.svg":["assets/magic_icons/277.svg"],"assets/magic_icons/278.svg":["assets/magic_icons/278.svg"],"assets/magic_icons/279.svg":["assets/magic_icons/279.svg"],"assets/magic_icons/28.svg":["assets/magic_icons/28.svg"],"assets/magic_icons/280.svg":["assets/magic_icons/280.svg"],"assets/magic_icons/281.svg":["assets/magic_icons/281.svg"],"assets/magic_icons/282.svg":["assets/magic_icons/282.svg"],"assets/magic_icons/283.svg":["assets/magic_icons/283.svg"],"assets/magic_icons/284.svg":["assets/magic_icons/284.svg"],"assets/magic_icons/285.svg":["assets/magic_icons/285.svg"],"assets/magic_icons/286.svg":["assets/magic_icons/286.svg"],"assets/magic_icons/287.svg":["assets/magic_icons/287.svg"],"assets/magic_icons/288.svg":["assets/magic_icons/288.svg"],"assets/magic_icons/289.svg":["assets/magic_icons/289.svg"],"assets/magic_icons/29.svg":["assets/magic_icons/29.svg"],"assets/magic_icons/290.svg":["assets/magic_icons/290.svg"],"assets/magic_icons/291.svg":["assets/magic_icons/291.svg"],"assets/magic_icons/292.svg":["assets/magic_icons/292.svg"],"assets/magic_icons/293.svg":["assets/magic_icons/293.svg"],"assets/magic_icons/294.svg":["assets/magic_icons/294.svg"],"assets/magic_icons/295.svg":["assets/magic_icons/295.svg"],"assets/magic_icons/296.svg":["assets/magic_icons/296.svg"],"assets/magic_icons/297.svg":["assets/magic_icons/297.svg"],"assets/magic_icons/298.svg":["assets/magic_icons/298.svg"],"assets/magic_icons/299.svg":["assets/magic_icons/299.svg"],"assets/magic_icons/3.svg":["assets/magic_icons/3.svg"],"assets/magic_icons/30.svg":["assets/magic_icons/30.svg"],"assets/magic_icons/300.svg":["assets/magic_icons/300.svg"],"assets/magic_icons/301.svg":["assets/magic_icons/301.svg"],"assets/magic_icons/302.svg":["assets/magic_icons/302.svg"],"assets/magic_icons/303.svg":["assets/magic_icons/303.svg"],"assets/magic_icons/304.svg":["assets/magic_icons/304.svg"],"assets/magic_icons/305.svg":["assets/magic_icons/305.svg"],"assets/magic_icons/306.svg":["assets/magic_icons/306.svg"],"assets/magic_icons/307.svg":["assets/magic_icons/307.svg"],"assets/magic_icons/308.svg":["assets/magic_icons/308.svg"],"assets/magic_icons/309.svg":["assets/magic_icons/309.svg"],"assets/magic_icons/31.svg":["assets/magic_icons/31.svg"],"assets/magic_icons/310.svg":["assets/magic_icons/310.svg"],"assets/magic_icons/311.svg":["assets/magic_icons/311.svg"],"assets/magic_icons/312.svg":["assets/magic_icons/312.svg"],"assets/magic_icons/313.svg":["assets/magic_icons/313.svg"],"assets/magic_icons/314.svg":["assets/magic_icons/314.svg"],"assets/magic_icons/315.svg":["assets/magic_icons/315.svg"],"assets/magic_icons/316.svg":["assets/magic_icons/316.svg"],"assets/magic_icons/317.svg":["assets/magic_icons/317.svg"],"assets/magic_icons/318.svg":["assets/magic_icons/318.svg"],"assets/magic_icons/319.svg":["assets/magic_icons/319.svg"],"assets/magic_icons/32.svg":["assets/magic_icons/32.svg"],"assets/magic_icons/320.svg":["assets/magic_icons/320.svg"],"assets/magic_icons/321.svg":["assets/magic_icons/321.svg"],"assets/magic_icons/322.svg":["assets/magic_icons/322.svg"],"assets/magic_icons/323.svg":["assets/magic_icons/323.svg"],"assets/magic_icons/324.svg":["assets/magic_icons/324.svg"],"assets/magic_icons/325.svg":["assets/magic_icons/325.svg"],"assets/magic_icons/326.svg":["assets/magic_icons/326.svg"],"assets/magic_icons/327.svg":["assets/magic_icons/327.svg"],"assets/magic_icons/328.svg":["assets/magic_icons/328.svg"],"assets/magic_icons/329.svg":["assets/magic_icons/329.svg"],"assets/magic_icons/33.svg":["assets/magic_icons/33.svg"],"assets/magic_icons/330.svg":["assets/magic_icons/330.svg"],"assets/magic_icons/331.svg":["assets/magic_icons/331.svg"],"assets/magic_icons/332.svg":["assets/magic_icons/332.svg"],"assets/magic_icons/333.svg":["assets/magic_icons/333.svg"],"assets/magic_icons/334.svg":["assets/magic_icons/334.svg"],"assets/magic_icons/335.svg":["assets/magic_icons/335.svg"],"assets/magic_icons/336.svg":["assets/magic_icons/336.svg"],"assets/magic_icons/337.svg":["assets/magic_icons/337.svg"],"assets/magic_icons/338.svg":["assets/magic_icons/338.svg"],"assets/magic_icons/339.svg":["assets/magic_icons/339.svg"],"assets/magic_icons/34.svg":["assets/magic_icons/34.svg"],"assets/magic_icons/35.svg":["assets/magic_icons/35.svg"],"assets/magic_icons/36.svg":["assets/magic_icons/36.svg"],"assets/magic_icons/37.svg":["assets/magic_icons/37.svg"],"assets/magic_icons/38.svg":["assets/magic_icons/38.svg"],"assets/magic_icons/39.svg":["assets/magic_icons/39.svg"],"assets/magic_icons/4.svg":["assets/magic_icons/4.svg"],"assets/magic_icons/40.svg":["assets/magic_icons/40.svg"],"assets/magic_icons/41.svg":["assets/magic_icons/41.svg"],"assets/magic_icons/42.svg":["assets/magic_icons/42.svg"],"assets/magic_icons/43.svg":["assets/magic_icons/43.svg"],"assets/magic_icons/44.svg":["assets/magic_icons/44.svg"],"assets/magic_icons/45.svg":["assets/magic_icons/45.svg"],"assets/magic_icons/46.svg":["assets/magic_icons/46.svg"],"assets/magic_icons/47.svg":["assets/magic_icons/47.svg"],"assets/magic_icons/48.svg":["assets/magic_icons/48.svg"],"assets/magic_icons/49.svg":["assets/magic_icons/49.svg"],"assets/magic_icons/5.svg":["assets/magic_icons/5.svg"],"assets/magic_icons/50.svg":["assets/magic_icons/50.svg"],"assets/magic_icons/51.svg":["assets/magic_icons/51.svg"],"assets/magic_icons/52.svg":["assets/magic_icons/52.svg"],"assets/magic_icons/53.svg":["assets/magic_icons/53.svg"],"assets/magic_icons/54.svg":["assets/magic_icons/54.svg"],"assets/magic_icons/55.svg":["assets/magic_icons/55.svg"],"assets/magic_icons/56.svg":["assets/magic_icons/56.svg"],"assets/magic_icons/57.svg":["assets/magic_icons/57.svg"],"assets/magic_icons/58.svg":["assets/magic_icons/58.svg"],"assets/magic_icons/59.svg":["assets/magic_icons/59.svg"],"assets/magic_icons/6.svg":["assets/magic_icons/6.svg"],"assets/magic_icons/60.svg":["assets/magic_icons/60.svg"],"assets/magic_icons/61.svg":["assets/magic_icons/61.svg"],"assets/magic_icons/62.svg":["assets/magic_icons/62.svg"],"assets/magic_icons/63.svg":["assets/magic_icons/63.svg"],"assets/magic_icons/64.svg":["assets/magic_icons/64.svg"],"assets/magic_icons/65.svg":["assets/magic_icons/65.svg"],"assets/magic_icons/66.svg":["assets/magic_icons/66.svg"],"assets/magic_icons/67.svg":["assets/magic_icons/67.svg"],"assets/magic_icons/68.svg":["assets/magic_icons/68.svg"],"assets/magic_icons/69.svg":["assets/magic_icons/69.svg"],"assets/magic_icons/7.svg":["assets/magic_icons/7.svg"],"assets/magic_icons/70.svg":["assets/magic_icons/70.svg"],"assets/magic_icons/71.svg":["assets/magic_icons/71.svg"],"assets/magic_icons/72.svg":["assets/magic_icons/72.svg"],"assets/magic_icons/73.svg":["assets/magic_icons/73.svg"],"assets/magic_icons/74.svg":["assets/magic_icons/74.svg"],"assets/magic_icons/75.svg":["assets/magic_icons/75.svg"],"assets/magic_icons/76.svg":["assets/magic_icons/76.svg"],"assets/magic_icons/77.svg":["assets/magic_icons/77.svg"],"assets/magic_icons/78.svg":["assets/magic_icons/78.svg"],"assets/magic_icons/79.svg":["assets/magic_icons/79.svg"],"assets/magic_icons/8.svg":["assets/magic_icons/8.svg"],"assets/magic_icons/80.svg":["assets/magic_icons/80.svg"],"assets/magic_icons/81.svg":["assets/magic_icons/81.svg"],"assets/magic_icons/82.svg":["assets/magic_icons/82.svg"],"assets/magic_icons/83.svg":["assets/magic_icons/83.svg"],"assets/magic_icons/84.svg":["assets/magic_icons/84.svg"],"assets/magic_icons/85.svg":["assets/magic_icons/85.svg"],"assets/magic_icons/86.svg":["assets/magic_icons/86.svg"],"assets/magic_icons/87.svg":["assets/magic_icons/87.svg"],"assets/magic_icons/88.svg":["assets/magic_icons/88.svg"],"assets/magic_icons/89.svg":["assets/magic_icons/89.svg"],"assets/magic_icons/9.svg":["assets/magic_icons/9.svg"],"assets/magic_icons/90.svg":["assets/magic_icons/90.svg"],"assets/magic_icons/91.svg":["assets/magic_icons/91.svg"],"assets/magic_icons/92.svg":["assets/magic_icons/92.svg"],"assets/magic_icons/93.svg":["assets/magic_icons/93.svg"],"assets/magic_icons/94.svg":["assets/magic_icons/94.svg"],"assets/magic_icons/95.svg":["assets/magic_icons/95.svg"],"assets/magic_icons/96.svg":["assets/magic_icons/96.svg"],"assets/magic_icons/97.svg":["assets/magic_icons/97.svg"],"assets/magic_icons/98.svg":["assets/magic_icons/98.svg"],"assets/magic_icons/99.svg":["assets/magic_icons/99.svg"],"assets/model-viewer.min.js":["assets/model-viewer.min.js"],"assets/models/Earth.gltf":["assets/models/Earth.gltf"],"assets/models/Earth.png":["assets/models/Earth.png"],"assets/models/Elephant.gltf":["assets/models/Elephant.gltf"],"assets/models/Elephant.png":["assets/models/Elephant.png"],"assets/models/Lungs.gltf":["assets/models/Lungs.gltf"],"assets/models/Lungs.png":["assets/models/Lungs.png"],"assets/models/Skull.gltf":["assets/models/Skull.gltf"],"assets/models/Skull.png":["assets/models/Skull.png"],"assets/pngs/ThumnailWriety.png":["assets/pngs/ThumnailWriety.png"],"assets/pngs/Wriety icon.png":["assets/pngs/Wriety icon.png"],"assets/pngs/add.png":["assets/pngs/add.png"],"assets/pngs/blue_folder.png":["assets/pngs/blue_folder.png"],"assets/pngs/canvas_default.png":["assets/pngs/canvas_default.png"],"assets/pngs/canvas_default_new.png":["assets/pngs/canvas_default_new.png"],"assets/pngs/compass_bg.png":["assets/pngs/compass_bg.png"],"assets/pngs/dashed_circle.png":["assets/pngs/dashed_circle.png"],"assets/pngs/down.png":["assets/pngs/down.png"],"assets/pngs/editSticky.png":["assets/pngs/editSticky.png"],"assets/pngs/google_search.png":["assets/pngs/google_search.png"],"assets/pngs/graph_bg.png":["assets/pngs/graph_bg.png"],"assets/pngs/image1.png":["assets/pngs/image1.png"],"assets/pngs/iwb.png":["assets/pngs/iwb.png"],"assets/pngs/jpg.png":["assets/pngs/jpg.png"],"assets/pngs/new_canvas_default.png":["assets/pngs/new_canvas_default.png"],"assets/pngs/new_main_bg.png":["assets/pngs/new_main_bg.png"],"assets/pngs/new_stickynotesBg.png":["assets/pngs/new_stickynotesBg.png"],"assets/pngs/noInternet.png":["assets/pngs/noInternet.png"],"assets/pngs/not_enough.png":["assets/pngs/not_enough.png"],"assets/pngs/pdf.png":["assets/pngs/pdf.png"],"assets/pngs/ppt.png":["assets/pngs/ppt.png"],"assets/pngs/presentation.png":["assets/pngs/presentation.png"],"assets/pngs/profile.png":["assets/pngs/profile.png"],"assets/pngs/record.png":["assets/pngs/record.png"],"assets/pngs/select.png":["assets/pngs/select.png"],"assets/pngs/selectall.png":["assets/pngs/selectall.png"],"assets/pngs/selected.png":["assets/pngs/selected.png"],"assets/pngs/selectedHistory.png":["assets/pngs/selectedHistory.png"],"assets/pngs/send.png":["assets/pngs/send.png"],"assets/pngs/share_icon_new.png":["assets/pngs/share_icon_new.png"],"assets/pngs/stickyNoteBg.png":["assets/pngs/stickyNoteBg.png"],"assets/pngs/stickyNoteflourescent.png":["assets/pngs/stickyNoteflourescent.png"],"assets/pngs/stickyNotesBg_new.png":["assets/pngs/stickyNotesBg_new.png"],"assets/pngs/stickyNotesIcon.png":["assets/pngs/stickyNotesIcon.png"],"assets/pngs/symmetri_five.svg":["assets/pngs/symmetri_five.svg"],"assets/pngs/symmetri_six.svg":["assets/pngs/symmetri_six.svg"],"assets/pngs/symmetri_three.svg":["assets/pngs/symmetri_three.svg"],"assets/pngs/symmetri_two.svg":["assets/pngs/symmetri_two.svg"],"assets/pngs/symmetry_eight.svg":["assets/pngs/symmetry_eight.svg"],"assets/pngs/symmetry_four.svg":["assets/pngs/symmetry_four.svg"],"assets/pngs/symmetry_nine.svg":["assets/pngs/symmetry_nine.svg"],"assets/pngs/symmetry_seven.svg":["assets/pngs/symmetry_seven.svg"],"assets/pngs/symmetry_ten.svg":["assets/pngs/symmetry_ten.svg"],"assets/pngs/template_checkbox.png":["assets/pngs/template_checkbox.png"],"assets/pngs/template_home.png":["assets/pngs/template_home.png"],"assets/pngs/ufo.png":["assets/pngs/ufo.png"],"assets/pngs/unselectedHistory.png":["assets/pngs/unselectedHistory.png"],"assets/pngs/up.png":["assets/pngs/up.png"],"assets/pngs/wriety.png":["assets/pngs/wriety.png"],"assets/pngs/wriety_ai.png":["assets/pngs/wriety_ai.png"],"assets/slides/copy.svg":["assets/slides/copy.svg"],"assets/slides/delete.svg":["assets/slides/delete.svg"],"assets/slides/share.svg":["assets/slides/share.svg"],"assets/svgs/BgTemplate8preview.svg":["assets/svgs/BgTemplate8preview.svg"],"assets/svgs/Image_new.svg":["assets/svgs/Image_new.svg"],"assets/svgs/Import_icon_new.svg":["assets/svgs/Import_icon_new.svg"],"assets/svgs/Vector.svg":["assets/svgs/Vector.svg"],"assets/svgs/VideolockIcon.svg":["assets/svgs/VideolockIcon.svg"],"assets/svgs/Videounlockicon.svg":["assets/svgs/Videounlockicon.svg"],"assets/svgs/add_rounded.svg":["assets/svgs/add_rounded.svg"],"assets/svgs/add_rounded_outline.svg":["assets/svgs/add_rounded_outline.svg"],"assets/svgs/add_template.svg":["assets/svgs/add_template.svg"],"assets/svgs/arrowback.svg":["assets/svgs/arrowback.svg"],"assets/svgs/back.svg":["assets/svgs/back.svg"],"assets/svgs/background.svg":["assets/svgs/background.svg"],"assets/svgs/backicon.svg":["assets/svgs/backicon.svg"],"assets/svgs/bgTemplate1.svg":["assets/svgs/bgTemplate1.svg"],"assets/svgs/bgTemplate10.svg":["assets/svgs/bgTemplate10.svg"],"assets/svgs/bgTemplate10_preview.svg":["assets/svgs/bgTemplate10_preview.svg"],"assets/svgs/bgTemplate11.svg":["assets/svgs/bgTemplate11.svg"],"assets/svgs/bgTemplate11_preview.svg":["assets/svgs/bgTemplate11_preview.svg"],"assets/svgs/bgTemplate12.svg":["assets/svgs/bgTemplate12.svg"],"assets/svgs/bgTemplate12_preview.svg":["assets/svgs/bgTemplate12_preview.svg"],"assets/svgs/bgTemplate13.svg":["assets/svgs/bgTemplate13.svg"],"assets/svgs/bgTemplate13_preview.svg":["assets/svgs/bgTemplate13_preview.svg"],"assets/svgs/bgTemplate14.svg":["assets/svgs/bgTemplate14.svg"],"assets/svgs/bgTemplate14_preview.svg":["assets/svgs/bgTemplate14_preview.svg"],"assets/svgs/bgTemplate2.svg":["assets/svgs/bgTemplate2.svg"],"assets/svgs/bgTemplate3.svg":["assets/svgs/bgTemplate3.svg"],"assets/svgs/bgTemplate4.svg":["assets/svgs/bgTemplate4.svg"],"assets/svgs/bgTemplate5.svg":["assets/svgs/bgTemplate5.svg"],"assets/svgs/bgTemplate6.svg":["assets/svgs/bgTemplate6.svg"],"assets/svgs/bgTemplate7.svg":["assets/svgs/bgTemplate7.svg"],"assets/svgs/bgTemplate8.svg":["assets/svgs/bgTemplate8.svg"],"assets/svgs/bgTemplate8_new.svg":["assets/svgs/bgTemplate8_new.svg"],"assets/svgs/bgTemplate9.svg":["assets/svgs/bgTemplate9.svg"],"assets/svgs/bgTemplate9_guides.svg":["assets/svgs/bgTemplate9_guides.svg"],"assets/svgs/bgTemplate9_guidesFull.svg":["assets/svgs/bgTemplate9_guidesFull.svg"],"assets/svgs/bgTemplate9_new.svg":["assets/svgs/bgTemplate9_new.svg"],"assets/svgs/bgTemplate_none.svg":["assets/svgs/bgTemplate_none.svg"],"assets/svgs/bgTemps.svg":["assets/svgs/bgTemps.svg"],"assets/svgs/bg_dots.svg":["assets/svgs/bg_dots.svg"],"assets/svgs/bg_lines.svg":["assets/svgs/bg_lines.svg"],"assets/svgs/bg_none.svg":["assets/svgs/bg_none.svg"],"assets/svgs/bg_squares.svg":["assets/svgs/bg_squares.svg"],"assets/svgs/bk_bg.svg":["assets/svgs/bk_bg.svg"],"assets/svgs/blue_folder.svg":["assets/svgs/blue_folder.svg"],"assets/svgs/board.svg":["assets/svgs/board.svg"],"assets/svgs/bold.svg":["assets/svgs/bold.svg"],"assets/svgs/booksicon.svg":["assets/svgs/booksicon.svg"],"assets/svgs/border_color.svg":["assets/svgs/border_color.svg"],"assets/svgs/brushicon.svg":["assets/svgs/brushicon.svg"],"assets/svgs/calculator.svg":["assets/svgs/calculator.svg"],"assets/svgs/camera.svg":["assets/svgs/camera.svg"],"assets/svgs/center_align.svg":["assets/svgs/center_align.svg"],"assets/svgs/circle.svg":["assets/svgs/circle.svg"],"assets/svgs/clock.svg":["assets/svgs/clock.svg"],"assets/svgs/close.svg":["assets/svgs/close.svg"],"assets/svgs/close_black.svg":["assets/svgs/close_black.svg"],"assets/svgs/cloud.svg":["assets/svgs/cloud.svg"],"assets/svgs/cloudImages.svg":["assets/svgs/cloudImages.svg"],"assets/svgs/color_fill.svg":["assets/svgs/color_fill.svg"],"assets/svgs/color_filler.svg":["assets/svgs/color_filler.svg"],"assets/svgs/compass.svg":["assets/svgs/compass.svg"],"assets/svgs/compass_bg.svg":["assets/svgs/compass_bg.svg"],"assets/svgs/cone.png":["assets/svgs/cone.png"],"assets/svgs/cone.svg":["assets/svgs/cone.svg"],"assets/svgs/cone_main.svg":["assets/svgs/cone_main.svg"],"assets/svgs/cone_main_new.svg":["assets/svgs/cone_main_new.svg"],"assets/svgs/contentPlayer_pen_new.svg":["assets/svgs/contentPlayer_pen_new.svg"],"assets/svgs/contentplayer_pen.svg":["assets/svgs/contentplayer_pen.svg"],"assets/svgs/copy.svg":["assets/svgs/copy.svg"],"assets/svgs/copy2.svg":["assets/svgs/copy2.svg"],"assets/svgs/copy_icon.svg":["assets/svgs/copy_icon.svg"],"assets/svgs/copy_to_all.svg":["assets/svgs/copy_to_all.svg"],"assets/svgs/crop.svg":["assets/svgs/crop.svg"],"assets/svgs/cube.png":["assets/svgs/cube.png"],"assets/svgs/cube.svg":["assets/svgs/cube.svg"],"assets/svgs/cube_bg.svg":["assets/svgs/cube_bg.svg"],"assets/svgs/cube_main.svg":["assets/svgs/cube_main.svg"],"assets/svgs/cube_main_new.svg":["assets/svgs/cube_main_new.svg"],"assets/svgs/cuboid.svg":["assets/svgs/cuboid.svg"],"assets/svgs/cylinder.png":["assets/svgs/cylinder.png"],"assets/svgs/cylinder.svg":["assets/svgs/cylinder.svg"],"assets/svgs/cylinder_main.svg":["assets/svgs/cylinder_main.svg"],"assets/svgs/cylinder_main_new.svg":["assets/svgs/cylinder_main_new.svg"],"assets/svgs/cylinderical_pyramid.svg":["assets/svgs/cylinderical_pyramid.svg"],"assets/svgs/dashed_pen.svg":["assets/svgs/dashed_pen.svg"],"assets/svgs/database_color.svg":["assets/svgs/database_color.svg"],"assets/svgs/database_white.svg":["assets/svgs/database_white.svg"],"assets/svgs/delete.svg":["assets/svgs/delete.svg"],"assets/svgs/delete_icon.svg":["assets/svgs/delete_icon.svg"],"assets/svgs/dice.svg":["assets/svgs/dice.svg"],"assets/svgs/divider_vert.svg":["assets/svgs/divider_vert.svg"],"assets/svgs/download_qr.svg":["assets/svgs/download_qr.svg"],"assets/svgs/drive_color.svg":["assets/svgs/drive_color.svg"],"assets/svgs/drive_white.svg":["assets/svgs/drive_white.svg"],"assets/svgs/dropBox.svg":["assets/svgs/dropBox.svg"],"assets/svgs/dropbox_color.svg":["assets/svgs/dropbox_color.svg"],"assets/svgs/dropbox_white.svg":["assets/svgs/dropbox_white.svg"],"assets/svgs/dustbin.svg":["assets/svgs/dustbin.svg"],"assets/svgs/editText.svg":["assets/svgs/editText.svg"],"assets/svgs/edit_icon.svg":["assets/svgs/edit_icon.svg"],"assets/svgs/editpencil.svg":["assets/svgs/editpencil.svg"],"assets/svgs/eight.svg":["assets/svgs/eight.svg"],"assets/svgs/erase.svg":["assets/svgs/erase.svg"],"assets/svgs/eraseAll.svg":["assets/svgs/eraseAll.svg"],"assets/svgs/eraseSelected.svg":["assets/svgs/eraseSelected.svg"],"assets/svgs/eraser.svg":["assets/svgs/eraser.svg"],"assets/svgs/eraser_bg.svg":["assets/svgs/eraser_bg.svg"],"assets/svgs/erasericon.svg":["assets/svgs/erasericon.svg"],"assets/svgs/exit.svg":["assets/svgs/exit.svg"],"assets/svgs/exit_icon.svg":["assets/svgs/exit_icon.svg"],"assets/svgs/export.svg":["assets/svgs/export.svg"],"assets/svgs/export_icon_new.svg":["assets/svgs/export_icon_new.svg"],"assets/svgs/file.svg":["assets/svgs/file.svg"],"assets/svgs/filtericon.svg":["assets/svgs/filtericon.svg"],"assets/svgs/five.svg":["assets/svgs/five.svg"],"assets/svgs/floder.svg":["assets/svgs/floder.svg"],"assets/svgs/folder.svg":["assets/svgs/folder.svg"],"assets/svgs/four.svg":["assets/svgs/four.svg"],"assets/svgs/front.svg":["assets/svgs/front.svg"],"assets/svgs/function.svg":["assets/svgs/function.svg"],"assets/svgs/google.svg":["assets/svgs/google.svg"],"assets/svgs/googleDrive.svg":["assets/svgs/googleDrive.svg"],"assets/svgs/graph.svg":["assets/svgs/graph.svg"],"assets/svgs/graph_bg.svg":["assets/svgs/graph_bg.svg"],"assets/svgs/graph_guides.svg":["assets/svgs/graph_guides.svg"],"assets/svgs/group 4856 new.svg":["assets/svgs/group 4856 new.svg"],"assets/svgs/hamburger.svg":["assets/svgs/hamburger.svg"],"assets/svgs/hand.svg":["assets/svgs/hand.svg"],"assets/svgs/handIcon.svg":["assets/svgs/handIcon.svg"],"assets/svgs/height.svg":["assets/svgs/height.svg"],"assets/svgs/historyicon.svg":["assets/svgs/historyicon.svg"],"assets/svgs/home.svg":["assets/svgs/home.svg"],"assets/svgs/horz_line.svg":["assets/svgs/horz_line.svg"],"assets/svgs/iFrame.svg":["assets/svgs/iFrame.svg"],"assets/svgs/icon group.svg":["assets/svgs/icon group.svg"],"assets/svgs/iframe_new.svg":["assets/svgs/iframe_new.svg"],"assets/svgs/image icon.svg":["assets/svgs/image icon.svg"],"assets/svgs/image.svg":["assets/svgs/image.svg"],"assets/svgs/imageCloud.svg":["assets/svgs/imageCloud.svg"],"assets/svgs/imageIcon.svg":["assets/svgs/imageIcon.svg"],"assets/svgs/images.svg":["assets/svgs/images.svg"],"assets/svgs/import.svg":["assets/svgs/import.svg"],"assets/svgs/info.svg":["assets/svgs/info.svg"],"assets/svgs/informationicon.svg":["assets/svgs/informationicon.svg"],"assets/svgs/iosSetting.svg":["assets/svgs/iosSetting.svg"],"assets/svgs/jpg.svg":["assets/svgs/jpg.svg"],"assets/svgs/leaderboard.svg":["assets/svgs/leaderboard.svg"],"assets/svgs/leftAlign.svg":["assets/svgs/leftAlign.svg"],"assets/svgs/left_arrow.svg":["assets/svgs/left_arrow.svg"],"assets/svgs/line.svg":["assets/svgs/line.svg"],"assets/svgs/localStorage.svg":["assets/svgs/localStorage.svg"],"assets/svgs/lock.svg":["assets/svgs/lock.svg"],"assets/svgs/logo.svg":["assets/svgs/logo.svg"],"assets/svgs/logo_new.svg":["assets/svgs/logo_new.svg"],"assets/svgs/magic_pen.svg":["assets/svgs/magic_pen.svg"],"assets/svgs/magicpen_new.svg":["assets/svgs/magicpen_new.svg"],"assets/svgs/magictoolhand.svg":["assets/svgs/magictoolhand.svg"],"assets/svgs/main_bg.svg":["assets/svgs/main_bg.svg"],"assets/svgs/marker.svg":["assets/svgs/marker.svg"],"assets/svgs/math.svg":["assets/svgs/math.svg"],"assets/svgs/math_bg.svg":["assets/svgs/math_bg.svg"],"assets/svgs/mathbox.svg":["assets/svgs/mathbox.svg"],"assets/svgs/menu.svg":["assets/svgs/menu.svg"],"assets/svgs/message_slave.svg":["assets/svgs/message_slave.svg"],"assets/svgs/messenger.svg":["assets/svgs/messenger.svg"],"assets/svgs/minimize.svg":["assets/svgs/minimize.svg"],"assets/svgs/mirror.svg":["assets/svgs/mirror.svg"],"assets/svgs/mirror1.svg":["assets/svgs/mirror1.svg"],"assets/svgs/more.svg":["assets/svgs/more.svg"],"assets/svgs/network_color.svg":["assets/svgs/network_color.svg"],"assets/svgs/network_white.svg":["assets/svgs/network_white.svg"],"assets/svgs/new_bgTemplate2.svg":["assets/svgs/new_bgTemplate2.svg"],"assets/svgs/new_bgTemplate3.svg":["assets/svgs/new_bgTemplate3.svg"],"assets/svgs/new_bgTemplate5.svg":["assets/svgs/new_bgTemplate5.svg"],"assets/svgs/new_bgTemplate7.svg":["assets/svgs/new_bgTemplate7.svg"],"assets/svgs/new_magic_tool.svg":["assets/svgs/new_magic_tool.svg"],"assets/svgs/nine.svg":["assets/svgs/nine.svg"],"assets/svgs/no_hand.svg":["assets/svgs/no_hand.svg"],"assets/svgs/no_message.svg":["assets/svgs/no_message.svg"],"assets/svgs/no_pen.svg":["assets/svgs/no_pen.svg"],"assets/svgs/no_present.svg":["assets/svgs/no_present.svg"],"assets/svgs/not_enough.svg":["assets/svgs/not_enough.svg"],"assets/svgs/object_Icon.svg":["assets/svgs/object_Icon.svg"],"assets/svgs/object_Icon_new.svg":["assets/svgs/object_Icon_new.svg"],"assets/svgs/objecticon.svg":["assets/svgs/objecticon.svg"],"assets/svgs/objects.svg":["assets/svgs/objects.svg"],"assets/svgs/objectviewericon.svg":["assets/svgs/objectviewericon.svg"],"assets/svgs/octogon.svg":["assets/svgs/octogon.svg"],"assets/svgs/one.svg":["assets/svgs/one.svg"],"assets/svgs/oneDrive.svg":["assets/svgs/oneDrive.svg"],"assets/svgs/onedrive_color.svg":["assets/svgs/onedrive_color.svg"],"assets/svgs/onedrive_white.svg":["assets/svgs/onedrive_white.svg"],"assets/svgs/palette.svg":["assets/svgs/palette.svg"],"assets/svgs/pallete_new.svg":["assets/svgs/pallete_new.svg"],"assets/svgs/parellelogram.svg":["assets/svgs/parellelogram.svg"],"assets/svgs/participantstext.svg":["assets/svgs/participantstext.svg"],"assets/svgs/participantsupload.svg":["assets/svgs/participantsupload.svg"],"assets/svgs/pause.svg":["assets/svgs/pause.svg"],"assets/svgs/pause_rounded.svg":["assets/svgs/pause_rounded.svg"],"assets/svgs/pdf.svg":["assets/svgs/pdf.svg"],"assets/svgs/pen.svg":["assets/svgs/pen.svg"],"assets/svgs/pen_slave.svg":["assets/svgs/pen_slave.svg"],"assets/svgs/pen_tool.svg":["assets/svgs/pen_tool.svg"],"assets/svgs/pencil_bg.svg":["assets/svgs/pencil_bg.svg"],"assets/svgs/pendrive_white.svg":["assets/svgs/pendrive_white.svg"],"assets/svgs/penicon.svg":["assets/svgs/penicon.svg"],"assets/svgs/pentagon.svg":["assets/svgs/pentagon.svg"],"assets/svgs/picture.svg":["assets/svgs/picture.svg"],"assets/svgs/play.svg":["assets/svgs/play.svg"],"assets/svgs/play_Icon.svg":["assets/svgs/play_Icon.svg"],"assets/svgs/play_rounded.svg":["assets/svgs/play_rounded.svg"],"assets/svgs/playicon.svg":["assets/svgs/playicon.svg"],"assets/svgs/potractor_bg.svg":["assets/svgs/potractor_bg.svg"],"assets/svgs/ppt.svg":["assets/svgs/ppt.svg"],"assets/svgs/presentation.svg":["assets/svgs/presentation.svg"],"assets/svgs/presenterbackicon.svg":["assets/svgs/presenterbackicon.svg"],"assets/svgs/prism.svg":["assets/svgs/prism.svg"],"assets/svgs/prism_main.svg":["assets/svgs/prism_main.svg"],"assets/svgs/prism_main_new.svg":["assets/svgs/prism_main_new.svg"],"assets/svgs/profile_menu.svg":["assets/svgs/profile_menu.svg"],"assets/svgs/protractor.svg":["assets/svgs/protractor.svg"],"assets/svgs/protractor_new.svg":["assets/svgs/protractor_new.svg"],"assets/svgs/pyramid.png":["assets/svgs/pyramid.png"],"assets/svgs/pyramid.svg":["assets/svgs/pyramid.svg"],"assets/svgs/pyramid_main.svg":["assets/svgs/pyramid_main.svg"],"assets/svgs/pyramid_main_new.svg":["assets/svgs/pyramid_main_new.svg"],"assets/svgs/quiz.svg":["assets/svgs/quiz.svg"],"assets/svgs/record.svg":["assets/svgs/record.svg"],"assets/svgs/recordSelected.svg":["assets/svgs/recordSelected.svg"],"assets/svgs/record_new.svg":["assets/svgs/record_new.svg"],"assets/svgs/rectangle.svg":["assets/svgs/rectangle.svg"],"assets/svgs/redo.svg":["assets/svgs/redo.svg"],"assets/svgs/redo2.svg":["assets/svgs/redo2.svg"],"assets/svgs/referencezoneIcon.svg":["assets/svgs/referencezoneIcon.svg"],"assets/svgs/remove.svg":["assets/svgs/remove.svg"],"assets/svgs/remove_bgTemplate.svg":["assets/svgs/remove_bgTemplate.svg"],"assets/svgs/restart.svg":["assets/svgs/restart.svg"],"assets/svgs/rightAlign.svg":["assets/svgs/rightAlign.svg"],"assets/svgs/right_arrow.svg":["assets/svgs/right_arrow.svg"],"assets/svgs/right_triangle.svg":["assets/svgs/right_triangle.svg"],"assets/svgs/rombus.svg":["assets/svgs/rombus.svg"],"assets/svgs/rotate.svg":["assets/svgs/rotate.svg"],"assets/svgs/ruler.svg":["assets/svgs/ruler.svg"],"assets/svgs/save.svg":["assets/svgs/save.svg"],"assets/svgs/save_all.svg":["assets/svgs/save_all.svg"],"assets/svgs/scale.svg":["assets/svgs/scale.svg"],"assets/svgs/scale1.svg":["assets/svgs/scale1.svg"],"assets/svgs/scale2.svg":["assets/svgs/scale2.svg"],"assets/svgs/scale_bg.svg":["assets/svgs/scale_bg.svg"],"assets/svgs/scanicon.svg":["assets/svgs/scanicon.svg"],"assets/svgs/screen_share.svg":["assets/svgs/screen_share.svg"],"assets/svgs/screenshot_color.svg":["assets/svgs/screenshot_color.svg"],"assets/svgs/search.svg":["assets/svgs/search.svg"],"assets/svgs/search2.svg":["assets/svgs/search2.svg"],"assets/svgs/selectedHistory.svg":["assets/svgs/selectedHistory.svg"],"assets/svgs/selection new.svg":["assets/svgs/selection new.svg"],"assets/svgs/selection.svg":["assets/svgs/selection.svg"],"assets/svgs/send.svg":["assets/svgs/send.svg"],"assets/svgs/set_square.png":["assets/svgs/set_square.png"],"assets/svgs/setsquare.svg":["assets/svgs/setsquare.svg"],"assets/svgs/setting.svg":["assets/svgs/setting.svg"],"assets/svgs/settings.svg":["assets/svgs/settings.svg"],"assets/svgs/settings_icon.svg":["assets/svgs/settings_icon.svg"],"assets/svgs/settings_new.svg":["assets/svgs/settings_new.svg"],"assets/svgs/seven.svg":["assets/svgs/seven.svg"],"assets/svgs/shapes.svg":["assets/svgs/shapes.svg"],"assets/svgs/shapesIcon.svg":["assets/svgs/shapesIcon.svg"],"assets/svgs/shapesbg.svg":["assets/svgs/shapesbg.svg"],"assets/svgs/share_icon.svg":["assets/svgs/share_icon.svg"],"assets/svgs/share_icon_new.svg":["assets/svgs/share_icon_new.svg"],"assets/svgs/simulationIcon_new.svg":["assets/svgs/simulationIcon_new.svg"],"assets/svgs/simulations.svg":["assets/svgs/simulations.svg"],"assets/svgs/six.svg":["assets/svgs/six.svg"],"assets/svgs/slides.svg":["assets/svgs/slides.svg"],"assets/svgs/sphere.svg":["assets/svgs/sphere.svg"],"assets/svgs/sphere_main.svg":["assets/svgs/sphere_main.svg"],"assets/svgs/square.svg":["assets/svgs/square.svg"],"assets/svgs/stickyNotes.svg":["assets/svgs/stickyNotes.svg"],"assets/svgs/stickynote_bg.svg":["assets/svgs/stickynote_bg.svg"],"assets/svgs/stop.svg":["assets/svgs/stop.svg"],"assets/svgs/stop_rounded.svg":["assets/svgs/stop_rounded.svg"],"assets/svgs/stop_watch.svg":["assets/svgs/stop_watch.svg"],"assets/svgs/student_exit.svg":["assets/svgs/student_exit.svg"],"assets/svgs/teacher_hand.svg":["assets/svgs/teacher_hand.svg"],"assets/svgs/teacher_message.svg":["assets/svgs/teacher_message.svg"],"assets/svgs/teacher_no_hand.svg":["assets/svgs/teacher_no_hand.svg"],"assets/svgs/teacher_no_message.svg":["assets/svgs/teacher_no_message.svg"],"assets/svgs/teacher_no_pen.svg":["assets/svgs/teacher_no_pen.svg"],"assets/svgs/teacher_pen.svg":["assets/svgs/teacher_pen.svg"],"assets/svgs/ten.svg":["assets/svgs/ten.svg"],"assets/svgs/text.svg":["assets/svgs/text.svg"],"assets/svgs/textSize.svg":["assets/svgs/textSize.svg"],"assets/svgs/texture.svg":["assets/svgs/texture.svg"],"assets/svgs/three.svg":["assets/svgs/three.svg"],"assets/svgs/toolbarswitch.svg":["assets/svgs/toolbarswitch.svg"],"assets/svgs/triangle.svg":["assets/svgs/triangle.svg"],"assets/svgs/two.svg":["assets/svgs/two.svg"],"assets/svgs/undo.svg":["assets/svgs/undo.svg"],"assets/svgs/undo2.svg":["assets/svgs/undo2.svg"],"assets/svgs/unlock.svg":["assets/svgs/unlock.svg"],"assets/svgs/unselectedHistory.svg":["assets/svgs/unselectedHistory.svg"],"assets/svgs/updateIcon.svg":["assets/svgs/updateIcon.svg"],"assets/svgs/upload.svg":["assets/svgs/upload.svg"],"assets/svgs/vert_line1.svg":["assets/svgs/vert_line1.svg"],"assets/svgs/vrhedseticon.svg":["assets/svgs/vrhedseticon.svg"],"assets/svgs/wand.svg":["assets/svgs/wand.svg"],"assets/svgs/webCam.svg":["assets/svgs/webCam.svg"],"assets/svgs/web_cam.svg":["assets/svgs/web_cam.svg"],"assets/svgs/widght.svg":["assets/svgs/widght.svg"],"assets/svgs/wriety.svg":["assets/svgs/wriety.svg"],"assets/svgs/wriety_ai.svg":["assets/svgs/wriety_ai.svg"],"assets/svgs/wriety_logo.svg":["assets/svgs/wriety_logo.svg"],"assets/svgs/youtubeIcon.svg":["assets/svgs/youtubeIcon.svg"],"assets/svgs/zoom_icon.svg":["assets/svgs/zoom_icon.svg"],"assets/template.html":["assets/template.html"],"assets/toolbar new icons/add.svg":["assets/toolbar new icons/add.svg"],"assets/toolbar new icons/chat.svg":["assets/toolbar new icons/chat.svg"],"assets/toolbar new icons/content.svg":["assets/toolbar new icons/content.svg"],"assets/toolbar new icons/eraser.svg":["assets/toolbar new icons/eraser.svg"],"assets/toolbar new icons/grid.svg":["assets/toolbar new icons/grid.svg"],"assets/toolbar new icons/hand.svg":["assets/toolbar new icons/hand.svg"],"assets/toolbar new icons/math.svg":["assets/toolbar new icons/math.svg"],"assets/toolbar new icons/media.svg":["assets/toolbar new icons/media.svg"],"assets/toolbar new icons/menu.svg":["assets/toolbar new icons/menu.svg"],"assets/toolbar new icons/participant.svg":["assets/toolbar new icons/participant.svg"],"assets/toolbar new icons/pen.svg":["assets/toolbar new icons/pen.svg"],"assets/toolbar new icons/qr.svg":["assets/toolbar new icons/qr.svg"],"assets/toolbar new icons/record.svg":["assets/toolbar new icons/record.svg"],"assets/toolbar new icons/redo.svg":["assets/toolbar new icons/redo.svg"],"assets/toolbar new icons/reference.svg":["assets/toolbar new icons/reference.svg"],"assets/toolbar new icons/reverse.svg":["assets/toolbar new icons/reverse.svg"],"assets/toolbar new icons/save.svg":["assets/toolbar new icons/save.svg"],"assets/toolbar new icons/selection.svg":["assets/toolbar new icons/selection.svg"],"assets/toolbar new icons/settings.svg":["assets/toolbar new icons/settings.svg"],"assets/toolbar new icons/shapes.svg":["assets/toolbar new icons/shapes.svg"],"assets/toolbar new icons/share.svg":["assets/toolbar new icons/share.svg"],"assets/toolbar new icons/text.svg":["assets/toolbar new icons/text.svg"],"assets/toolbar new icons/undo.svg":["assets/toolbar new icons/undo.svg"],"assets/toolbar new/add.svg":["assets/toolbar new/add.svg"],"assets/toolbar new/drm.svg":["assets/toolbar new/drm.svg"],"assets/toolbar new/eraser.svg":["assets/toolbar new/eraser.svg"],"assets/toolbar new/grid.svg":["assets/toolbar new/grid.svg"],"assets/toolbar new/hand.svg":["assets/toolbar new/hand.svg"],"assets/toolbar new/media.svg":["assets/toolbar new/media.svg"],"assets/toolbar new/menu.svg":["assets/toolbar new/menu.svg"],"assets/toolbar new/pen.svg":["assets/toolbar new/pen.svg"],"assets/toolbar new/redo.svg":["assets/toolbar new/redo.svg"],"assets/toolbar new/reference.svg":["assets/toolbar new/reference.svg"],"assets/toolbar new/selection.svg":["assets/toolbar new/selection.svg"],"assets/toolbar new/shapes.svg":["assets/toolbar new/shapes.svg"],"assets/toolbar new/switch dark.svg":["assets/toolbar new/switch dark.svg"],"assets/toolbar new/switch light.svg":["assets/toolbar new/switch light.svg"],"assets/toolbar new/text.svg":["assets/toolbar new/text.svg"],"assets/toolbar new/undo.svg":["assets/toolbar new/undo.svg"],"fonts/poppins/Poppins-Black.ttf":["fonts/poppins/Poppins-Black.ttf"],"fonts/poppins/Poppins-BlackItalic.ttf":["fonts/poppins/Poppins-BlackItalic.ttf"],"fonts/poppins/Poppins-Bold.ttf":["fonts/poppins/Poppins-Bold.ttf"],"fonts/poppins/Poppins-BoldItalic.ttf":["fonts/poppins/Poppins-BoldItalic.ttf"],"fonts/poppins/Poppins-ExtraBold.ttf":["fonts/poppins/Poppins-ExtraBold.ttf"],"fonts/poppins/Poppins-ExtraBoldItalic.ttf":["fonts/poppins/Poppins-ExtraBoldItalic.ttf"],"fonts/poppins/Poppins-ExtraLight.ttf":["fonts/poppins/Poppins-ExtraLight.ttf"],"fonts/poppins/Poppins-ExtraLightItalic.ttf":["fonts/poppins/Poppins-ExtraLightItalic.ttf"],"fonts/poppins/Poppins-Italic.ttf":["fonts/poppins/Poppins-Italic.ttf"],"fonts/poppins/Poppins-Light.ttf":["fonts/poppins/Poppins-Light.ttf"],"fonts/poppins/Poppins-LightItalic.ttf":["fonts/poppins/Poppins-LightItalic.ttf"],"fonts/poppins/Poppins-Medium.ttf":["fonts/poppins/Poppins-Medium.ttf"],"fonts/poppins/Poppins-MediumItalic.ttf":["fonts/poppins/Poppins-MediumItalic.ttf"],"fonts/poppins/Poppins-Regular.ttf":["fonts/poppins/Poppins-Regular.ttf"],"fonts/poppins/Poppins-SemiBold.ttf":["fonts/poppins/Poppins-SemiBold.ttf"],"fonts/poppins/Poppins-SemiBoldItalic.ttf":["fonts/poppins/Poppins-SemiBoldItalic.ttf"],"fonts/poppins/Poppins-Thin.ttf":["fonts/poppins/Poppins-Thin.ttf"],"fonts/poppins/Poppins-ThinItalic.ttf":["fonts/poppins/Poppins-ThinItalic.ttf"],"packages/cupertino_icons/assets/CupertinoIcons.ttf":["packages/cupertino_icons/assets/CupertinoIcons.ttf"]}